smooth_trajectory/__init__.py
smooth_trajectory/trajectory.py
smooth_trajectory/utilities.py
smooth_trajectory-0.1.0.dist-info/METADATA
smooth_trajectory-0.1.0.dist-info/WHEEL
smooth_trajectory-0.1.0.dist-info/top_level.txt
smooth_trajectory-0.1.0.dist-info/RECORD
