Metadata-Version: 2.1
Name: smooth-trajectory
Version: 0.1.0
Summary: A package for generating straight line trajectories in SE(3) with time scaling for smoothness
Author-email: Ozan Tokatli <ozan.tokatli@gmail.com>
Project-URL: Homepage, https://github.com/otokatli/pySmoothTrajectory
Classifier: Programming Language :: Python :: 3
Classifier: License :: OSI Approved :: MIT License
Classifier: Operating System :: OS Independent
Classifier: Development Status :: 3 - Alpha
Classifier: Intended Audience :: Science/Research
Requires-Python: >=3.6
Requires-Dist: numpy
Requires-Dist: scipy
